setup.cfg
setup.py
jsonresume/__init__.py
jsonresume/exceptions.py
jsonresume/resume.py
jsonresume/schema/__init__.py
jsonresume/schema/resume.py
jsonresume/schema/validators.py
jsonresume/schema/components/__init__.py
jsonresume/schema/components/ability.py
jsonresume/schema/components/achievement.py
jsonresume/schema/components/common.py
jsonresume/schema/components/experience.py
jsonresume/schema/components/personal.py
jsonresume/tests/__init__.py
jsonresume/tests/test_resume.py
jsonresume/tests/test_schema.py
jsonresume/tests/test_validators.py
jsonresume/tests/fixtures/__init__.py
jsonresume/tests/fixtures/load.py
jsonresume_validator.egg-info/PKG-INFO
jsonresume_validator.egg-info/SOURCES.txt
jsonresume_validator.egg-info/dependency_links.txt
jsonresume_validator.egg-info/not-zip-safe
jsonresume_validator.egg-info/requires.txt
jsonresume_validator.egg-info/top_level.txt