Metadata-Version: 1.1
Name: jsonresume-validator
Version: 0.1.5
Summary: validates JSON resumes
Home-page: https://github.com/kelvintaywl/jsonresume-validator
Author: Kelvin Tay
Author-email: kelvintay@gmail.com
License: UNKNOWN
Download-URL: https://github.com/kelvintaywl/jsonresume-validator/tarball/0.1.5
Keywords: jsonresume,validation,colander
Platform: UNKNOWN
